{
  "name": "betrix-ui",
  "version": "2.0.0",
  "type": "module",
  "description": "BETRIX - Global Sports AI Platform",
  "main": "src/worker-final.js",
  "engines": {
    "node": ">=20.0.0"
  },
  "scripts": {
    "start": "node src/worker-final.js",
    "dev": "node src/worker-db.js",
    "worker": "node src/worker-final.js",
    "test": "node --test tests/*.js",
    "redis:validate": "node scripts/validate-redis-connection.js",
    "redis:monitor": "node scripts/monitor-redis-health.js",
    "redis:test-handlers": "node scripts/test-redis-handlers.js",
    "redis:health": "npm run redis:validate && npm run redis:test-handlers"
  },
  "dependencies": {
    "@google/generative-ai": "^0.24.1",
    "@paypal/checkout-server-sdk": "^1.0.3",
    "bcryptjs": "^3.0.3",
    "body-parser": "^1.20.3",
    "bull": "^4.16.5",
    "bullmq": "^5.64.1",
    "chalk": "^5.6.2",
    "cheerio": "^1.0.0-rc.12",
    "compression": "^1.8.1",
    "cors": "^2.8.5",
    "csv-parse": "^5.4.0",
    "dotenv": "^17.2.3",
    "drizzle-orm": "^0.44.7",
    "express": "^4.21.2",
    "express-rate-limit": "^8.2.1",
    "helmet": "^8.1.0",
    "ioredis": "^5.8.2",
    "joi": "^18.0.2",
    "morgan": "^1.10.1",
    "multer": "^2.0.2",
    "node-cron": "^3.0.3",
    "node-fetch": "^3.3.2",
    "pg": "^8.16.3",
    "telegraf": "^4.16.3",
    "twilio": "^5.10.6",
    "ws": "^8.18.3"
  },
  "keywords": [
    "telegram",
    "bot",
    "sports",
    "ai",
    "betting",
    "global"
  ],
  "author": "BETRIX Team",
  "license": "MIT"
}
